naughty_string_validator/__init__.py
naughty_string_validator/naughty_string_validator.py
naughty_string_validator/naughty_string_db/blns.json
naughty_string_validator/naughty_string_db/emoji.json
naughty_string_validator/utils/__init__.py
naughty_string_validator/utils/file_utils.py
naughty_string_validator-0.1.7.dist-info/AUTHORS.rst
naughty_string_validator-0.1.7.dist-info/LICENSE
naughty_string_validator-0.1.7.dist-info/METADATA
naughty_string_validator-0.1.7.dist-info/WHEEL
naughty_string_validator-0.1.7.dist-info/top_level.txt
naughty_string_validator-0.1.7.dist-info/RECORD
