Metadata-Version: 2.1
Name: naughty-string-validator
Version: 0.1.7
Summary: A library that returns naughty strings     from an offline database of Big List of Naughty Strings & emojis
Home-page: https://github.com/shashikumarraja/naughty_string_validator_python
Author: Shashi Kumar Raja
Author-email: shashiraja92@gmail.com
License: MIT
Keywords: naughty strings emoji unicode
Platform: UNKNOWN
Classifier: Development Status :: 4 - Beta
Classifier: Intended Audience :: Developers
Classifier: License :: OSI Approved :: MIT License
Classifier: Natural Language :: English
Classifier: Programming Language :: Python :: 2.7
Classifier: Programming Language :: Python :: 3.5
Classifier: Programming Language :: Python :: 3.6
Classifier: Programming Language :: Python :: 3.7
Classifier: Programming Language :: Python :: 3.8
Classifier: Programming Language :: Python :: Implementation :: PyPy
